{"v":5,"entries":{"components-button--docs":{"id":"components-button--docs","title":"components/Button","name":"Docs","importPath":"./lib/components/Button/Button.stories.tsx","type":"docs","tags":["dev","test","autodocs"],"storiesImports":[]},"components-button--default":{"type":"story","id":"components-button--default","name":"Default","title":"components/Button","importPath":"./lib/components/Button/Button.stories.tsx","componentPath":"./lib/components/Button/Button.tsx","tags":["dev","test","autodocs"]},"components-capacitybar--docs":{"id":"components-capacitybar--docs","title":"Components/CapacityBar","name":"Docs","importPath":"./lib/components/CapacityBar/CapacityBar.stories.tsx","type":"docs","tags":["dev","test","autodocs"],"storiesImports":[]},"components-capacitybar--one-usage-capacity":{"type":"story","id":"components-capacitybar--one-usage-capacity","name":"One Usage Capacity","title":"Components/CapacityBar","importPath":"./lib/components/CapacityBar/CapacityBar.stories.tsx","componentPath":"./lib/components/CapacityBar/CapacityBar.tsx","tags":["dev","test","autodocs"]},"components-capacitybar--two-usage-capacity":{"type":"story","id":"components-capacitybar--two-usage-capacity","name":"Two Usage Capacity","title":"Components/CapacityBar","importPath":"./lib/components/CapacityBar/CapacityBar.stories.tsx","componentPath":"./lib/components/CapacityBar/CapacityBar.tsx","tags":["dev","test","autodocs"]},"components-charcounter--docs":{"id":"components-charcounter--docs","title":"Components/CharCounter","name":"Docs","importPath":"./lib/components/CharCounter/CharCounter.stories.tsx","type":"docs","tags":["dev","test","autodocs"],"storiesImports":[]},"components-charcounter--default":{"type":"story","id":"components-charcounter--default","name":"Default","title":"Components/CharCounter","importPath":"./lib/components/CharCounter/CharCounter.stories.tsx","componentPath":"./lib/components/CharCounter/CharCounter.tsx","tags":["dev","test","autodocs"]},"components-circularprogress--docs":{"id":"components-circularprogress--docs","title":"components/CircularProgress","name":"Docs","importPath":"./lib/components/CircularProgress/CircularProgress.stories.tsx","type":"docs","tags":["dev","test","autodocs"],"storiesImports":[]},"components-circularprogress--default":{"type":"story","id":"components-circularprogress--default","name":"Default","title":"components/CircularProgress","importPath":"./lib/components/CircularProgress/CircularProgress.stories.tsx","componentPath":"./lib/components/CircularProgress/CircularProgress.tsx","tags":["dev","test","autodocs"]},"components-closebutton--docs":{"id":"components-closebutton--docs","title":"Components/CloseButton","name":"Docs","importPath":"./lib/components/CloseButton/CloseButton.stories.tsx","type":"docs","tags":["dev","test","autodocs"],"storiesImports":[]},"components-closebutton--default":{"type":"story","id":"components-closebutton--default","name":"Default","title":"Components/CloseButton","importPath":"./lib/components/CloseButton/CloseButton.stories.tsx","componentPath":"./lib/components/CloseButton/CloseButton.tsx","tags":["dev","test","autodocs"]},"components-collapsible--docs":{"id":"components-collapsible--docs","title":"Components/Collapsible","name":"Docs","importPath":"./lib/components/Collapsible/Collapsible.stories.tsx","type":"docs","tags":["dev","test","autodocs"],"storiesImports":[]},"components-collapsible--default":{"type":"story","id":"components-collapsible--default","name":"Default","title":"Components/Collapsible","importPath":"./lib/components/Collapsible/Collapsible.stories.tsx","componentPath":"./lib/components/Collapsible/Collapsible.tsx","tags":["dev","test","autodocs"]},"components-cursortooltip--docs":{"id":"components-cursortooltip--docs","title":"Components/CursorTooltip","name":"Docs","importPath":"./lib/components/CursorTooltip/CursorTooltip.stories.tsx","type":"docs","tags":["dev","test","autodocs"],"storiesImports":[]},"components-cursortooltip--default":{"type":"story","id":"components-cursortooltip--default","name":"Default","title":"Components/CursorTooltip","importPath":"./lib/components/CursorTooltip/CursorTooltip.stories.tsx","componentPath":"./lib/components/CursorTooltip/CursorTooltip.tsx","tags":["dev","test","autodocs"]},"components-datetimepicker--docs":{"id":"components-datetimepicker--docs","title":"Components/DateTimePicker","name":"Docs","importPath":"./lib/components/DateTimePicker/DateTimePicker.stories.tsx","type":"docs","tags":["dev","test","autodocs"],"storiesImports":[]},"components-datetimepicker--default":{"type":"story","id":"components-datetimepicker--default","name":"Default","title":"Components/DateTimePicker","importPath":"./lib/components/DateTimePicker/DateTimePicker.stories.tsx","componentPath":"./lib/components/DateTimePicker/DateTimePicker.tsx","tags":["dev","test","autodocs"]},"components-emptypagemessage--docs":{"id":"components-emptypagemessage--docs","title":"Components/EmptyPageMessage","name":"Docs","importPath":"./lib/components/EmptyPageMessage/EmptyPageMessage.stories.tsx","type":"docs","tags":["dev","test","autodocs"],"storiesImports":[]},"components-emptypagemessage--default":{"type":"story","id":"components-emptypagemessage--default","name":"Default","title":"Components/EmptyPageMessage","importPath":"./lib/components/EmptyPageMessage/EmptyPageMessage.stories.tsx","componentPath":"./lib/components/EmptyPageMessage/EmptyPageMessage.tsx","tags":["dev","test","autodocs"]},"components-errorpage--docs":{"id":"components-errorpage--docs","title":"Components/ErrorPage","name":"Docs","importPath":"./lib/components/ErrorPage/ErrorPage.stories.tsx","type":"docs","tags":["dev","test","autodocs"],"storiesImports":[]},"components-errorpage--default":{"type":"story","id":"components-errorpage--default","name":"Default","title":"Components/ErrorPage","importPath":"./lib/components/ErrorPage/ErrorPage.stories.tsx","componentPath":"./lib/components/ErrorPage/ErrorPage.tsx","tags":["dev","test","autodocs"]},"components-formwrapperdialog--docs":{"id":"components-formwrapperdialog--docs","title":"Components/FormWrapperDialog","name":"Docs","importPath":"./lib/components/FormWrapperDialog/FormWrapperDialog.stories.tsx","type":"docs","tags":["dev","test","autodocs"],"storiesImports":[]},"components-formwrapperdialog--default":{"type":"story","id":"components-formwrapperdialog--default","name":"Default","title":"Components/FormWrapperDialog","importPath":"./lib/components/FormWrapperDialog/FormWrapperDialog.stories.tsx","componentPath":"./lib/components/FormWrapperDialog/FormWrapperDialog.tsx","tags":["dev","test","autodocs"]},"components-info--docs":{"id":"components-info--docs","title":"Components/Info","name":"Docs","importPath":"./lib/components/Info/Info.stories.tsx","type":"docs","tags":["dev","test","autodocs"],"storiesImports":[]},"components-info--default":{"type":"story","id":"components-info--default","name":"Default","title":"Components/Info","importPath":"./lib/components/Info/Info.stories.tsx","componentPath":"./lib/components/Info/Info.tsx","tags":["dev","test","autodocs"]},"components-loader--docs":{"id":"components-loader--docs","title":"Components/Loader","name":"Docs","importPath":"./lib/components/Loader/Loader.stories.tsx","type":"docs","tags":["dev","test","autodocs"],"storiesImports":[]},"components-loader--default":{"type":"story","id":"components-loader--default","name":"Default","title":"Components/Loader","importPath":"./lib/components/Loader/Loader.stories.tsx","componentPath":"./lib/components/Loader/Loader.tsx","tags":["dev","test","autodocs"]},"components-menupopper--docs":{"id":"components-menupopper--docs","title":"Components/MenuPopper","name":"Docs","importPath":"./lib/components/MenuPopper/MenuPopper.stories.tsx","type":"docs","tags":["dev","test","autodocs"],"storiesImports":[]},"components-menupopper--menu-popper":{"type":"story","id":"components-menupopper--menu-popper","name":"Menu Popper","title":"Components/MenuPopper","importPath":"./lib/components/MenuPopper/MenuPopper.stories.tsx","componentPath":"./lib/components/MenuPopper/MenuPopper.tsx","tags":["dev","test","autodocs"]},"components-newpasswordtooltip--docs":{"id":"components-newpasswordtooltip--docs","title":"Components/NewPasswordTooltip","name":"Docs","importPath":"./lib/components/NewPasswordTooltip/NewPasswordTooltip.stories.tsx","type":"docs","tags":["dev","test","autodocs"],"storiesImports":[]},"components-newpasswordtooltip--default":{"type":"story","id":"components-newpasswordtooltip--default","name":"Default","title":"Components/NewPasswordTooltip","importPath":"./lib/components/NewPasswordTooltip/NewPasswordTooltip.stories.tsx","componentPath":"./lib/components/NewPasswordTooltip/NewPasswordTooltip.tsx","tags":["dev","test","autodocs"]},"components-scheduleselector--docs":{"id":"components-scheduleselector--docs","title":"Components/ScheduleSelector","name":"Docs","importPath":"./lib/components/ScheduleSelector/ScheduleSelector.stories.tsx","type":"docs","tags":["dev","test","autodocs"],"storiesImports":[]},"components-scheduleselector--default":{"type":"story","id":"components-scheduleselector--default","name":"Default","title":"Components/ScheduleSelector","importPath":"./lib/components/ScheduleSelector/ScheduleSelector.stories.tsx","componentPath":"./lib/components/ScheduleSelector/ScheduleSelector.tsx","tags":["dev","test","autodocs"]},"components-sideblock--docs":{"id":"components-sideblock--docs","title":"Components/SideBlock","name":"Docs","importPath":"./lib/components/SideBlock/SideBlock.stories.tsx","type":"docs","tags":["dev","test","autodocs"],"storiesImports":[]},"components-sideblock--side-block":{"type":"story","id":"components-sideblock--side-block","name":"Side Block","title":"Components/SideBlock","importPath":"./lib/components/SideBlock/SideBlock.stories.tsx","componentPath":"./lib/components/SideBlock/SideBlock.tsx","tags":["dev","test","autodocs"]},"components-signinwithgoogle--docs":{"id":"components-signinwithgoogle--docs","title":"Components/SignInWithGoogle","name":"Docs","importPath":"./lib/components/SignInWithGoogle/SignInWithGoogle.stories.tsx","type":"docs","tags":["dev","test","autodocs"],"storiesImports":[]},"components-signinwithgoogle--default":{"type":"story","id":"components-signinwithgoogle--default","name":"Default","title":"Components/SignInWithGoogle","importPath":"./lib/components/SignInWithGoogle/SignInWithGoogle.stories.tsx","componentPath":"./lib/components/SignInWithGoogle/SignInWithGoogle.tsx","tags":["dev","test","autodocs"]},"components-singletoggle--docs":{"id":"components-singletoggle--docs","title":"Components/SingleToggle","name":"Docs","importPath":"./lib/components/SingleToggle/SingleToggle.stories.tsx","type":"docs","tags":["dev","test","autodocs"],"storiesImports":[]},"components-singletoggle--single-toggle":{"type":"story","id":"components-singletoggle--single-toggle","name":"Single Toggle","title":"Components/SingleToggle","importPath":"./lib/components/SingleToggle/SingleToggle.stories.tsx","componentPath":"./lib/components/SingleToggle/SingleToggle.tsx","tags":["dev","test","autodocs"]},"components-spantooltip--docs":{"id":"components-spantooltip--docs","title":"Components/SpanTooltip","name":"Docs","importPath":"./lib/components/SpanTooltip/SpanTooltip.stories.tsx","type":"docs","tags":["dev","test","autodocs"],"storiesImports":[]},"components-spantooltip--default":{"type":"story","id":"components-spantooltip--default","name":"Default","title":"Components/SpanTooltip","importPath":"./lib/components/SpanTooltip/SpanTooltip.stories.tsx","componentPath":"./lib/components/SpanTooltip/SpanTooltip.tsx","tags":["dev","test","autodocs"]},"components-spinner--docs":{"id":"components-spinner--docs","title":"Components/Spinner","name":"Docs","importPath":"./lib/components/Spinner/Spinner.stories.tsx","type":"docs","tags":["dev","test","autodocs"],"storiesImports":[]},"components-spinner--default":{"type":"story","id":"components-spinner--default","name":"Default","title":"Components/Spinner","importPath":"./lib/components/Spinner/Spinner.stories.tsx","componentPath":"./lib/components/Spinner/Spinner.tsx","tags":["dev","test","autodocs"]},"components-switch--docs":{"id":"components-switch--docs","title":"Components/Switch","name":"Docs","importPath":"./lib/components/Switch/Switch.stories.tsx","type":"docs","tags":["dev","test","autodocs"],"storiesImports":[]},"components-switch--default":{"type":"story","id":"components-switch--default","name":"Default","title":"Components/Switch","importPath":"./lib/components/Switch/Switch.stories.tsx","componentPath":"./lib/components/Switch/Switch.tsx","tags":["dev","test","autodocs"]},"components-table--docs":{"id":"components-table--docs","title":"Components/Table","name":"Docs","importPath":"./lib/components/Table/Table.stories.tsx","type":"docs","tags":["dev","test","autodocs"],"storiesImports":[]},"components-table--default":{"type":"story","id":"components-table--default","name":"Default","title":"Components/Table","importPath":"./lib/components/Table/Table.stories.tsx","componentPath":"./lib/components/Table/Table.tsx","tags":["dev","test","autodocs"]},"components-texteditor--docs":{"id":"components-texteditor--docs","title":"components/TextEditor","name":"Docs","importPath":"./lib/components/TextEditor/TextEditor.stories.tsx","type":"docs","tags":["dev","test","autodocs"],"storiesImports":[]},"components-texteditor--default":{"type":"story","id":"components-texteditor--default","name":"Default","title":"components/TextEditor","importPath":"./lib/components/TextEditor/TextEditor.stories.tsx","componentPath":"./lib/components/TextEditor/TextEditor.tsx","tags":["dev","test","autodocs"]},"components-toasterdialog--docs":{"id":"components-toasterdialog--docs","title":"Components/ToasterDialog","name":"Docs","importPath":"./lib/components/ToasterDialog/ToasterDialog.stories.tsx","type":"docs","tags":["dev","test","autodocs"],"storiesImports":[]},"components-toasterdialog--dialog":{"type":"story","id":"components-toasterdialog--dialog","name":"Dialog","title":"Components/ToasterDialog","importPath":"./lib/components/ToasterDialog/ToasterDialog.stories.tsx","componentPath":"./lib/components/ToasterDialog/ToasterDialog.tsx","tags":["dev","test","autodocs"]},"components-toasterdialog--toaster":{"type":"story","id":"components-toasterdialog--toaster","name":"Toaster","title":"Components/ToasterDialog","importPath":"./lib/components/ToasterDialog/ToasterDialog.stories.tsx","componentPath":"./lib/components/ToasterDialog/ToasterDialog.tsx","tags":["dev","test","autodocs"]},"components-togglebutton--docs":{"id":"components-togglebutton--docs","title":"Components/ToggleButton","name":"Docs","importPath":"./lib/components/ToggleButton/ToggleButton.stories.tsx","type":"docs","tags":["dev","test","autodocs"],"storiesImports":[]},"components-togglebutton--toggle-button":{"type":"story","id":"components-togglebutton--toggle-button","name":"Toggle Button","title":"Components/ToggleButton","importPath":"./lib/components/ToggleButton/ToggleButton.stories.tsx","componentPath":"./lib/components/ToggleButton/ToggleButton.tsx","tags":["dev","test","autodocs"]},"components-tooltip--docs":{"id":"components-tooltip--docs","title":"Components/Tooltip","name":"Docs","importPath":"./lib/components/Tooltip/Tooltip.stories.tsx","type":"docs","tags":["dev","test","autodocs"],"storiesImports":[]},"components-tooltip--default":{"type":"story","id":"components-tooltip--default","name":"Default","title":"Components/Tooltip","importPath":"./lib/components/Tooltip/Tooltip.stories.tsx","componentPath":"./lib/components/Tooltip/Tooltip.tsx","tags":["dev","test","autodocs"]},"components-inputs-checkbox--docs":{"id":"components-inputs-checkbox--docs","title":"components/inputs/Checkbox","name":"Docs","importPath":"./lib/components/inputs/Checkbox/Checkbox.stories.tsx","type":"docs","tags":["dev","test","autodocs"],"storiesImports":[]},"components-inputs-checkbox--default":{"type":"story","id":"components-inputs-checkbox--default","name":"Default","title":"components/inputs/Checkbox","importPath":"./lib/components/inputs/Checkbox/Checkbox.stories.tsx","componentPath":"./lib/components/inputs/Checkbox/Checkbox.tsx","tags":["dev","test","autodocs"]},"components-inputs-searchfield--docs":{"id":"components-inputs-searchfield--docs","title":"Components/inputs/SearchField","name":"Docs","importPath":"./lib/components/inputs/SearchField/SearchField.stories.tsx","type":"docs","tags":["dev","test","autodocs"],"storiesImports":[]},"components-inputs-searchfield--search-field":{"type":"story","id":"components-inputs-searchfield--search-field","name":"Search Field","title":"Components/inputs/SearchField","importPath":"./lib/components/inputs/SearchField/SearchField.stories.tsx","componentPath":"./lib/components/inputs/SearchField/SearchField.tsx","tags":["dev","test","autodocs"]},"components-inputs-select--docs":{"id":"components-inputs-select--docs","title":"Components/inputs/Select","name":"Docs","importPath":"./lib/components/inputs/Select/Select.stories.tsx","type":"docs","tags":["dev","test","autodocs"],"storiesImports":[]},"components-inputs-select--default":{"type":"story","id":"components-inputs-select--default","name":"Default","title":"Components/inputs/Select","importPath":"./lib/components/inputs/Select/Select.stories.tsx","componentPath":"./lib/components/inputs/Select/Select.tsx","tags":["dev","test","autodocs"]},"components-inputs-tagsbox--docs":{"id":"components-inputs-tagsbox--docs","title":"Components/inputs/TagsBox","name":"Docs","importPath":"./lib/components/inputs/TagsBox/TagsBox.stories.tsx","type":"docs","tags":["dev","test","autodocs"],"storiesImports":[]},"components-inputs-tagsbox--default":{"type":"story","id":"components-inputs-tagsbox--default","name":"Default","title":"Components/inputs/TagsBox","importPath":"./lib/components/inputs/TagsBox/TagsBox.stories.tsx","componentPath":"./lib/components/inputs/TagsBox/TagsBox.tsx","tags":["dev","test","autodocs"]},"components-inputs-textarea--docs":{"id":"components-inputs-textarea--docs","title":"components/inputs/TextArea","name":"Docs","importPath":"./lib/components/inputs/TextArea/TextArea.stories.tsx","type":"docs","tags":["dev","test","autodocs"],"storiesImports":[]},"components-inputs-textarea--default":{"type":"story","id":"components-inputs-textarea--default","name":"Default","title":"components/inputs/TextArea","importPath":"./lib/components/inputs/TextArea/TextArea.stories.tsx","componentPath":"./lib/components/inputs/TextArea/TextArea.tsx","tags":["dev","test","autodocs"]},"components-inputs-uploadfield--docs":{"id":"components-inputs-uploadfield--docs","title":"components/inputs/UploadField","name":"Docs","importPath":"./lib/components/inputs/UploadField/UploadField.stories.tsx","type":"docs","tags":["dev","test","autodocs"],"storiesImports":[]},"components-inputs-uploadfield--default":{"type":"story","id":"components-inputs-uploadfield--default","name":"Default","title":"components/inputs/UploadField","importPath":"./lib/components/inputs/UploadField/UploadField.stories.tsx","componentPath":"./lib/components/inputs/UploadField/UploadField.tsx","tags":["dev","test","autodocs"]},"components-inputs-uploadfield--with-description":{"type":"story","id":"components-inputs-uploadfield--with-description","name":"With Description","title":"components/inputs/UploadField","importPath":"./lib/components/inputs/UploadField/UploadField.stories.tsx","componentPath":"./lib/components/inputs/UploadField/UploadField.tsx","tags":["dev","test","autodocs"]}}}